[
  {
    "id": "course-foundation-degree-healthcare-assistant-practitioner",
    "text": "Course: Foundation Degree Healthcare Assistant Practitioner\nCourse Code: FD-HAP-25/26\nLevel: L4/L5\nDuration: 2 years (Full Time or Part Time)\nDepartment: Education, Health and Law\nSub-Department: Health\n\nCourse Description:\nThis programme is designed to develop the skills and attributes needed for the role of the Healthcare Assistant Practitioner. Assistant Practitioners work as part of the wider health and social care team and have direct contact with patients, service users or clients providing high quality and compassionate care. Assistant Practitioners work at a level above that of Healthcare Support Workers and have a more in-depth understanding about factors that influence health and ill-health (e.g., anatomy and physiology). The programme will enable students to obtain the core skills, knowledge and values/behaviours to become an Assistant Practitioner.",
    "metadata": {
      "type": "course_overview",
      "course_code": "FD-HAP-25/26",
      "course_title": "Foundation Degree Healthcare Assistant Practitioner",
      "level": "L4/L5",
      "duration": "2 years (Full Time or Part Time)",
      "department": "Education, Health and Law",
      "sub_department": "Health",
      "credits": "220"
    }
  },
  {
    "id": "module-academic-research-and-study-skills",
    "text": "Module: Academic Research and Study Skills\nModule Code: W_HTH4C042R-2025.26\nModule Tutor: Shelley Sanderson\nCredits: 20\nYear: 1\nSemester: 1\n\nLearning Outcomes:\nLearning outcomes\\nOn completion of this module students will be able to:\\nKnowledge and Understanding: LO1 Describe and explain key theories of learning and development. (K1)\\nCognitive and Intellectual Skills: LO2 Discuss the relevance of learning theories to your role when working in healthcare. (C2)\\nKey Transferable Skills: LO3 Reflect on the importance of effective communication to share complex information in a professional environment (T1)\n\nModule Description:\nModule Descriptor: The module will provide students with the underpinning skills, theories and knowledge required for undergraduate study. This will also be transferable to their professional practice and provide a framework for their academic progress. This module aims to;\\n● Develop academic study skills including research and referencing\\n● Provide subject specific skills to enable them to succeed in their studies and the professional environment.",
    "metadata": {
      "type": "module",
      "module_code": "W_HTH4C042R-2025.26",
      "module_title": "Academic Research and Study Skills",
      "tutor": "Shelley Sanderson",
      "credits": "20",
      "year": "1",
      "semester": "1",
      "course_code": "FD-HAP-25/26",
      "sub_department": "Health"
    }
  },
  {
    "id": "assessment-academic-research-and-study-skills-essay",
    "text": "Assessment: Essay that addresses relevant learning theories within the Assistant Practitioner Role (1800 words) (60%)\nModule: Academic Research and Study Skills\nModule Code: W_HTH4C042R-2025.26\nAcademic Year: 1\nUnit Assessor: Shelley Sanderson\nSubmission Location: Electronic Via Turnitin\nDeadline: 14th November 2025\nSubmission Format: [Turnitin/Physical/Face-to-Face]\n\nLearning Outcomes:\nLO 1, 2\n\nAssessment Brief:\nTask 1 - Essay (60%) – Learning Outcomes 1 & 2 (1800 words)\\nTo demonstrate your achievement of the learning outcomes for this module you will write an essay that includes the following;\\n● A description of the key learning theories explored in class e.g. learning styles,\\nmultiple intelligence. Explain how these theories can affect your own style of learning and your work in the hospital or community\\nsetting.\\n● Ensure your essay follows the academic conventions of the level of the course.",
    "metadata": {
      "type": "assessment",
      "module_code": "W_HTH4C042R-2025.26",
      "module_title": "Academic Research and Study Skills",
      "assessment_type": "Essay",
      "weight": "60%",
      "word_count": "1800 words",
      "deadline": "14th November 2025",
      "year": "1",
      "semester": "1",
      "tutor": "Shelley Sanderson"
    }
  },
  {
    "id": "assessment-academic-research-and-study-skills-electronic-presentation",
    "text": "Assessment: 10 minute electronic presentation using a reflective model which explains the essential communication skills required within the professional environment. (40%)\nModule: Academic Research and Study Skills\nModule Code: W_HTH4C042R-2025.26\nAcademic Year: 1\nUnit Assessor: Shelley Sanderson\nSubmission Location: Electronic Via Turnitin\nDeadline: 9th January 2026\nSubmission Format: [Turnitin/Physical/Face-to-Face]\n\nLearning Outcomes:\nLO 3\n\nAssessment Brief:\nTask 2 - Electronic Presentation including Q&A (40%) Learning Outcomes 3 (10 minutes)\\nCreate and present an electronic presentation to a small group of your peers which demonstrates reflections on your own\\npractice.\\nFocus on communication skills in the workplace, written and verbal, and to individuals and groups.",
    "metadata": {
      "type": "assessment",
      "module_code": "W_HTH4C042R-2025.26",
      "module_title": "Academic Research and Study Skills",
      "assessment_type": "Electronic Presentation",
      "weight": "40%",
      "word_count": "10 minutes",
      "deadline": "9th January 2026",
      "year": "1",
      "semester": "1",
      "tutor": "Shelley Sanderson"
    }
  }
]