[
    {
        "id": "course-foundation-degree-in-health-play-specialism",
        "text": "Course: Foundation Degree in Health Play Specialism\nCourse Code: FD-HPS-25/26\nLevel: Undergraduate Foundation Course\nDuration: 2 year course\nDepartment: Education, Health and Law\nSub-Department: Health\n\nCourse Description:\nUnderstand and analyse general and therapeutic play and apply this knowledge and information to inform the development of care, developmental and therapeutic play plans for the individual baby, child and young person\\nevaluating therapeutic play techniques to support treatments and interventions within the role of a Health Play Specialist\\nBe able to appropriately conduct general and therapeutic play to support procedures, treatments, therapy, or other actions safely and effectively.\\nBe able to select appropriate play resources and provide a full range of general and therapeutic play activities that reflect the particular needs of service-users",
        "metadata": {
          "type": "course_overview",
          "course_code": "FD-HPS-25/26",
          "course_title": "Foundation Degree in Health Play Specialism",
          "level": "Undergraduate Foundation Course",
          "duration": "2 year course",
          "department": "Education, Health and Law",
          "sub_department": "Health",
          "credits": "240"
        }
      },
      {
        "id": "module-communication-and-interpersonal-skills",
        "text": "Module: Communication and Interpersonal Skills\nModule Code: W_HTH4C023R-2025.26\nModule Tutor: Shelley Sanderson\nCredits: 20\nYear: 1\nSemester: 2\n\nLearning Outcomes:\nLearning outcomes\\nOn completion of this module students will be able to:\\nKnowledge and Understanding:\\n1. Discuss a range of communication approaches, interpersonal and intrapersonal practices to support children, young people and families (K2).\\nCognitive and Intellectual skills:\\n2. Analyse professional situations in order to select and utilise appropriate communication styles, maintaining professional boundaries when working with children, young people and families (C2).\\nProfessional Skills:\\n3. Demonstrate effective communication techniques derived from evidence-based practice to ensure the best outcomes for babies, children, young people and vulnerable individuals (P2).\\nKey Transferable Skills:\\n4. Reflect on own practice in relation to communication skills and identify strengths and areas for development (T1).\\n5. Demonstrate effective contribution to team working (T4).\n\nModule Description:\nModule Descriptor: This module will develop students’ communication and interpersonal skills in preparation for registration as a Health Play Specialist. This module aims to: · Enable students to acquire and develop a range of skills and knowledge required to communicate effectively, including both interpersonal and intrapersonal practices.\\n\\n· Develop reflection on professional communication, applying theoretical knowledge to enhance team working skills and promote ethical working practices · Provide opportunities for the development of an understanding of the fundamental principles of communication and the ways in which context and content may influence approaches.",
        "metadata": {
          "type": "module",
          "module_code": "W_HTH4C023R-2025.26",
          "module_title": "Communication and Interpersonal Skills",
          "tutor": "Shelley Sanderson",
          "credits": "20",
          "year": "1",
          "semester": "2",
          "course_code": "FD-HPS-25/26",
          "sub_department": "Health"
        }
      },
      {
        "id": "assessment-communication-and-interpersonal-skills-e-portfolio",
        "text": "Assessment: E- Portfolio (3000 words) 100%\nModule: Communication and Interpersonal Skills\nModule Code: W_HTH4C023R-2025.26\nAcademic Year: 1\nUnit Assessor: Shelley Sanderson\nSubmission Location: [Blackboard/Classroom/etc]\nDeadline: Week 29\nSubmission Format: [Turnitin/Physical/Face-to-Face]\n\nLearning Outcomes:\nLO 1, 2, 3, 4, 5\n\nAssessment Brief:\nAssessment Brief\\nTask 1: Communication and Interpersonal Competencies CI 1 - 6 (3000 words) 100% 1, 2, 3, 4\\nYour assessment will be compiled of two observations (500 words each), three reflections (450 words each) and one short report (300 words).\\nThe theories delivered within the module will feature throughout your evidence, ensuring that all learning outcomes are met.\\n● You will need to discuss how effective your communication skills are when working with children, young people and other professionals in\\nthe workplace setting and in meeting their needs.\\n● Make reference to relevant theory and the underlying principles of effective communication.\\n● Discuss, evaluate and reflect how you have deployed these communication skills and techniques when supporting children and young\\npeople.\\n● Discuss the application of confidentiality to ethical work-based practices.",
        "metadata": {
          "type": "assessment",
          "module_code": "W_HTH4C023R-2025.26",
          "module_title": "Communication and Interpersonal Skills",
          "assessment_type": "E- Portfolio",
          "weight": "100%",
          "word_count": "3000 words",
          "deadline": "Week 29",
          "year": "1",
          "semester": "2",
          "tutor": "Shelley Sanderson"
        }
      },
      {
        "id": "module-developing-professional-practice-professional-occupational-standard",
        "text": "Module: Developing Professional Practice (Professional Occupational Standard)\nModule Code: W_HTH4C025R-2025.26\nModule Tutor: Paula Jackson\nCredits: 40\nYear: 1\nSemester: 1 and 2\n\nLearning Outcomes:\nLearning outcomes  \\nOn completion of this module students will be able to:  \\n\\nKnowledge and Understanding:  \\nDiscuss theoretical underpinnings and evolving principles guiding best practice when implementing play supporting sick babies, children, young people, and vulnerable individuals. (K1)\\nInterpret relevant safeguarding legislation, policy and procedures within your scope of practice (K3)\\n\\nCognitive and Intellectual Skills:  \\nExplain how innovative approaches influence ethical work practices within the healthcare sector, drawing on practice experience. (C1)\\n\\nProfessional Skills:  \\nDemonstrate competency in SoHPS Professional Occupational Standards as defined at level 4 (P1).\\n\\nKey Transferable Skills:  \\nDemonstrate developing autonomy with reducing need for supervision (T2) \\nCommunicate clearly, fluently and effectively with others (T3).\n\nModule Description:\nThis module will enable students to develop the professional occupational standards at Level 4, as defined by Society of Health Play Specialists (SoHPS) in the practice assessment competencies, to allow progression to Year 2 Level 5, and ultimately professional registration. The module will provide theoretical knowledge and apply this to professional practice in the workplace.\\n\\nThe module aims to - \\nProvide students with comprehensive knowledge of the Health Play Specialist's role, equipping them with a deeper understanding of the Health Play Specialist's contributions to the healthcare setting. \\nDevelop a clear understanding of best practices when working with sick babies, children, young people, and vulnerable individuals.  \\nProvide clinical practice experiences, enabling self-assessment and reflection, where students will create personal development plans to enhance their knowledge, skills, and behaviours.",
        "metadata": {
          "type": "module",
          "module_code": "W_HTH4C025R-2025.26",
          "module_title": "Developing Professional Practice (Professional Occupational Standard)",
          "tutor": "Paula Jackson",
          "credits": "40",
          "year": "1",
          "semester": "1 and 2",
          "course_code": "FD-HPS-25/26",
          "sub_department": "Health"
        }
      },
      {
        "id": "assessment-developing-professional-practice-professional-occupational-standard-e-portfolio-practice-assessment-competencies",
        "text": "Assessment: Task 1 ePortfolio: Practice Assessment Competencies (6000 words) 100%\nModule: Developing Professional Practice (Professional Occupational Standard)\nModule Code: W_HTH4C025R-2025.26\nAcademic Year: 1\nUnit Assessor: Paula Jackson\nSubmission Location: [Blackboard/Classroom/etc]\nDeadline: Week 30\nSubmission Format: [Turnitin/Physical/Face-to-Face]\n\nLearning Outcomes:\nLO 1, 2, 3, 4, 5, 6\n\nAssessment Brief:\nComplete within ePortfolio evidence and sign off for progress to Year 2, Level 5 of learning - \\nInitial Workplace Interview\\nOrientation to the Place of Work\\nAll competency evidence completed and scored\\nAll competencies achieved at a pass (competency score of 2 or 3)\\nThe 200 hours of clinical practice\\nStudent Self-Assessment \\nFormative - End of Semester 1 Review\\nFinal Review - End of Year 2\\nMentor Assessment\\nFormative - End of Semester 1 Review\\nFinal Review - End of Year 2",
        "metadata": {
          "type": "assessment",
          "module_code": "W_HTH4C025R-2025.26",
          "module_title": "Developing Professional Practice (Professional Occupational Standard)",
          "assessment_type": "ePortfolio: Practice Assessment Competencies",
          "weight": "100%",
          "word_count": "6000 words",
          "deadline": "Week 30",
          "year": "1",
          "semester": "1 and 2",
          "tutor": "Paula Jackson"
        }
      },
      {
        "id": "module-developmental-approaches-to-play",
        "text": "Module: Developmental Approaches to Play\nModule Code: W_HTH4C021R-2025.26\nModule Tutor: Paula Jackson\nCredits: 20\nYear: 1\nSemester: 2\n\nLearning Outcomes:\nLearning outcomes On completion of this module students will be able to: Knowledge and Understanding: 1. Describe and use a range of developmental theories to discuss children’s development and their relevance to play (K1). Cognitive and Intellectual Skills: 2. Discuss a range of sources which inform ethical practices when observing, assessing, planning and supporting the developmental needs of babies, children, young people and vulnerable individuals (C1). Professional Skills: 3. Explain principles of evidence-based practice and how they guide developmentally appropriate play-based interventions, evaluating play programmes to meet the holistic developmental needs of sick babies, children, young people. (P2). 4. Demonstrate an innovative and creative approach to planned interventions (P3) Key Transferable Skills: 5. Develop autonomy in delivering developmentally appropriate play-based interventions. (T2).\\n6. Collaborate effectively with the multidisciplinary team to assess, plan, implement and evaluate developmentally appropriate play programmes (T4).\n\nModule Description:\nModule Descriptor: This module will focus on core principles of child development and the significance of play across the life span, with specific focus on its application within healthcare context. Key theories of child development will be explored and how play serves as a vital tool for developmental growth and wellbeing. The module will develop the learners understanding of the role of the Health Play Specialist in utilising and adapting developmental play approaches to\\nsupport babies, children and young people facing health challenges. This module aims to: ● Enable learners to recognise and support children’s holistic development through play. ● Develop an awareness of factors impacting on play, understanding the impact of health, illness and hospitalisation on development and play opportunities. ● Advocate play and a rights-based approach for babies, children and young people.",
        "metadata": {
          "type": "module",
          "module_code": "W_HTH4C021R-2025.26",
          "module_title": "Developmental Approaches to Play",
          "tutor": "Paula Jackson",
          "credits": "20",
          "year": "1",
          "semester": "2",
          "course_code": "FD-HPS-25/26",
          "sub_department": "Health"
        }
      },
      {
        "id": "assessment-developmental-approaches-to-play-e-portfolio-practice-assessment-competencies",
        "text": "Assessment: Task 1 ePortfolio Practice Assessment Competencies (1500 words) 50%\nModule: Developmental Approaches to Play\nModule Code: W_HTH4C021R-2025.26\nAcademic Year: 1\nUnit Assessor: Paula Jackson\nSubmission Location: [Blackboard/Classroom/etc]\nDeadline: Week 24\nSubmission Format: [Turnitin/Physical/Face-to-Face]\n\nLearning Outcomes:\nLO 1, 2, 3\n\nAssessment Brief:\n[Missing Data]",
        "metadata": {
          "type": "assessment",
          "module_code": "W_HTH4C021R-2025.26",
          "module_title": "Developmental Approaches to Play",
          "assessment_type": "ePortfolio Practice Assessment Competencies",
          "weight": "50%",
          "word_count": "1500 words",
          "deadline": "Week 24",
          "year": "1",
          "semester": "2",
          "tutor": "Paula Jackson"
        }
      },
      {
        "id": "assessment-developmental-approaches-to-play-e-portfolio-practice-assessment-competencies",
        "text": "Assessment: Task 2 ePortfolio Practice Assessment Competencies (1500 words) 50%\nModule: Developmental Approaches to Play\nModule Code: W_HTH4C021R-2025.26\nAcademic Year: 1\nUnit Assessor: Paula Jackson\nSubmission Location: [Blackboard/Classroom/etc]\nDeadline: Week 28\nSubmission Format: [Turnitin/Physical/Face-to-Face]\n\nLearning Outcomes:\nLO 4, 5, 6\n\nAssessment Brief:\n[Missing Data]",
        "metadata": {
          "type": "assessment",
          "module_code": "W_HTH4C021R-2025.26",
          "module_title": "Developmental Approaches to Play",
          "assessment_type": "ePortfolio Practice Assessment Competencies",
          "weight": "50%",
          "word_count": "1500 words",
          "deadline": "Week 28",
          "year": "1",
          "semester": "2",
          "tutor": "Paula Jackson"
        }
      },
      {
        "id": "module-safeguarding-children-and-vulnerable-young-people",
        "text": "Module: Safeguarding Children and Vulnerable Young People\nModule Code: W_HTH4C024R-2025.26\nModule Tutor: Ben Doughty\nCredits: 20\nYear: 1\nSemester: 1\n\nLearning Outcomes:\n21 Learning outcomes On completion of this module students will be able to:\\nKnowledge and Understanding:\\n1. Discuss best practice when safeguarding children,\\nwhilst involving parents/carers, colleagues and other\\nprofessional agencies within a hospital setting (K3).\\nCognitive and Intellectual Skills:\\n2. Discuss theories in relation to identifying\\nvulnerability to abuse and the signs and symptoms\\nwithin complex social structures (C2).\\nProfessional Skills:\\n3. Discuss historic safeguarding cases and how these\\nhave informed new ways of working that make\\nbabies, children, young people and vulnerable\\nindividuals safer whilst accessing hospital services\\n(P1).\\nTransferable Skills\\n4. Reflect upon your own professional role working\\nwithin a team in the context of safeguarding babies,\\nchildren, young people and vulnerable individuals\\nand supporting their families as a health play\\nspecialist (T1).\n\nModule Description:\nModule Descriptor:\\nThis module investigates aspects of safeguarding babies,\\nchildren, young people and vulnerable individuals, which is\\nfundamental to working with sick babies and children in a\\nhealthcare setting. It explores how to work effectively in a\\nmultidisciplinary team to support families and protect\\nindividuals.\\nThis module aims to:\\n● Enable students to gain knowledge and understanding\\nof safeguarding babies, children, young people and\\nvulnerable individuals.\\n● Develop best practice in supporting families within the\\nlegislative framework in a healthcare setting.\\n● Allow students to reflect and learn from historic\\nsafeguarding cases and apply this to their own practice.",
        "metadata": {
          "type": "module",
          "module_code": "W_HTH4C024R-2025.26",
          "module_title": "Safeguarding Children and Vulnerable Young People",
          "tutor": "Ben Doughty",
          "credits": "20",
          "year": "1",
          "semester": "1",
          "course_code": "FD-HPS-25/26",
          "sub_department": "Health"
        }
      },
      {
        "id": "assessment-safeguarding-children-and-vulnerable-young-people-presentation",
        "text": "Assessment: Presentation (15 minutes) 50%\nModule: Safeguarding Children and Vulnerable Young People\nModule Code: W_HTH4C024R-2025.26\nAcademic Year: 1\nUnit Assessor: Ben Doughty\nSubmission Location: [Blackboard/Classroom/etc]\nDeadline: Week 8\nSubmission Format: [Turnitin/Physical/Face-to-Face]\n\nLearning Outcomes:\nLO 1, 2\n\nAssessment Brief:\nTask 1: Presentation (15 minutes) 50%\\nDescribe safeguarding practices within a hospital setting, focussing on children and young\\npeople. Use examples to discuss how these practices can be implemented and how these\\nmight impact on those involved (including families and other professionals).\\nDescribe how at least two theories could be applied to and example used above. Compare and\\ncontrast these theories in relation to vulnerability to abuse and the signs and symptoms within\\ncomplex social structures.\\nPlease ensure that your presentation is effectively supported with appropriate references\\nand includes a reference list.",
        "metadata": {
          "type": "assessment",
          "module_code": "W_HTH4C024R-2025.26",
          "module_title": "Safeguarding Children and Vulnerable Young People",
          "assessment_type": "Presentation",
          "weight": "50%",
          "word_count": "[Missing Data]",
          "deadline": "Week 8",
          "year": "1",
          "semester": "1",
          "tutor": "Ben Doughty"
        }
      },
      {
        "id": "assessment-safeguarding-children-and-vulnerable-young-people-report",
        "text": "Assessment: Report (1500 words) 50%.\nModule: Safeguarding Children and Vulnerable Young People\nModule Code: W_HTH4C024R-2025.26\nAcademic Year: 1\nUnit Assessor: Ben Doughty\nSubmission Location: [Blackboard/Classroom/etc]\nDeadline: Week 15\nSubmission Format: [Turnitin/Physical/Face-to-Face]\n\nLearning Outcomes:\nLO 3, 4\n\nAssessment Brief:\nTask 2: Report (1500 words) 50%.\\nSelect a historical case which has been professionally reviews (either through and SCR or\\npublic inquiry). Describe the failings of these cases and discuss how health professionals can\\nlearn from them to make babies, children, young people and vulnerable individuals safer whilst\\naccessing hospital services.\\nFinish the report with a reflection on your own professional role working within a team in the\\ncontext of safeguarding babies, children, young people and vulnerable individuals and\\nsupporting their families as a health play specialist.\\nPlease ensure that your report is effectively supported with appropriate references and\\nincludes a reference list.",
        "metadata": {
          "type": "assessment",
          "module_code": "W_HTH4C024R-2025.26",
          "module_title": "Safeguarding Children and Vulnerable Young People",
          "assessment_type": "Report",
          "weight": "50%",
          "word_count": "1500",
          "deadline": "Week 15",
          "year": "1",
          "semester": "1",
          "tutor": "Ben Doughty"
        }
      },
      {
        "id": "module-academic-and-digital-skills",
        "text": "Module: Academic and Digital Skills\nModule Code: W_HTH4C001R-2025.26\nModule Tutor: Ben Doughty\nCredits: 20\nYear: 1\nSemester: 1\n\nLearning Outcomes:\n21 Learning outcomes On completion of this module students will be able to: Knowledge and Understanding: 1. Explain ways of developing academic and digital skills relevant to the health sector (K2). Professional Skills: 2. Discuss innovative practice in health roles, drawing on multiple sources of evidence (P3). Key Transferable Skills: 3. Reflect on personal and professional skills, focussing on communication and digital literacy (T1). 4. Communicate effectively using contemporary methods (T3).\n\nModule Description:\nModule Descriptor: The module will provide students with the underpinning skills required for undergraduate study. These skills will be transferable to their professional development journey and provide a framework to support their academic progress. The aim of this module is to: · Develop academic study skills including research and referencing.\\n\\n· Facilitate the development of core digital skills required for study which can be transferred into practical work environments. · Provide subject specific skills to enable them to succeed in their studies.",
        "metadata": {
          "type": "module",
          "module_code": "W_HTH4C001R-2025.26",
          "module_title": "Academic and Digital Skills",
          "tutor": "Ben Doughty",
          "credits": "20",
          "year": "1",
          "semester": "1",
          "course_code": "FD-HPS-25/26",
          "sub_department": "Health"
        }
      },
      {
        "id": "assessment-academic-and-digital-skills-essay",
        "text": "Assessment: Task 1 - Essay (50%) – Learning Outcomes 1 & 2 (1500 words)\nModule: Academic and Digital Skills\nModule Code: W_HTH4C001R-2025.26\nAcademic Year: 1\nUnit Assessor: Ben Doughty\nSubmission Location: [Blackboard/Classroom/etc]\nDeadline: Week 9\nSubmission Format: [Turnitin/Physical/Face-to-Face]\n\nLearning Outcomes:\nLearning Outcomes 1 & 2\n\nAssessment Brief:\nTo demonstrate your achievement of the learning outcomes for this module you will write an\\nessay that includes the following:\\n● You should research and discuss contemporary and innovative practice within the\\nhealth and wellbeing sector. For example, how are health and wellbeing practitioners\\nusing technology to engage with service users and stakeholders? How are these new\\nways of working enhancing service provision?\\n● With reference to working in the health and wellbeing sector, explain ways of\\ndeveloping your academic and digital skills to meet current working practices. This\\ncould include remote working technologies.\\nEvidence of your research for this report must be included in the form of references\\nand a reference list (excluded from the word count).",
        "metadata": {
          "type": "assessment",
          "module_code": "W_HTH4C001R-2025.26",
          "module_title": "Academic and Digital Skills",
          "assessment_type": "Essay",
          "weight": "50%",
          "word_count": "1500 words",
          "deadline": "Week 9",
          "year": "1",
          "semester": "1",
          "tutor": "Ben Doughty"
        }
      },
      {
        "id": "assessment-academic-and-digital-skills-electronic-presentation",
        "text": "Assessment: Task 2 - Electronic Presentation including Q&A (50%) Learning Outcomes 3 & 4 (15 minutes)\nModule: Academic and Digital Skills\nModule Code: W_HTH4C001R-2025.26\nAcademic Year: 1\nUnit Assessor: Ben Doughty\nSubmission Location: [Blackboard/Classroom/etc]\nDeadline: Week 14\nSubmission Format: [Turnitin/Physical/Face-to-Face]\n\nLearning Outcomes:\nLearning Outcomes 3 & 4\n\nAssessment Brief:\nCreate and present an electronic presentation to a small group of your peers which\\ndemonstrates reflections on your own personal and professional practice.\\nFocus on communication skills in the workplace, written, verbal, and the use of technology.\\nYou should include communication with individuals and groups.\\nEvidence of your research for this report must be included in the form of references\\nand a reference list (excluded from the word count).",
        "metadata": {
          "type": "assessment",
          "module_code": "W_HTH4C001R-2025.26",
          "module_title": "Academic and Digital Skills",
          "assessment_type": "Electronic Presentation",
          "weight": "50%",
          "word_count": "15 minutes",
          "deadline": "Week 14",
          "year": "1",
          "semester": "1",
          "tutor": "Ben Doughty"
        }
      },
      {
        "id": "module-ethical-working-practices-in-healthcare",
        "text": "Module: Ethical Working Practices in Healthcare\nModule Code: W_HTH5C027R-2025.26\nModule Tutor: Shelley Sanderson\nCredits: 20\nYear: 2\nSemester: 1\n\nLearning Outcomes:\n21 Learning outcomes On completion of this module students will be able to: Knowledge and Understanding: 1. Evaluate approaches adopted to address ethical dilemmas where they have emerged in clinical practice (K2). 2. Analyse the impact of safeguarding legislation, policy and procedures and ethical perspectives on decision making within the healthcare sector (K3) Professional Skills: 3. Evaluate clinical situations in order to make informed and appropriate judgements in relation to ethical dilemmas in the healthcare sector (P1). Key Transferable Skills 4. Communicate clearly, fluently and professionally (T3).\n\nModule Description:\nModule Descriptor: This module provides the opportunity to explore complex dilemmas in decision making regarding treatment and care of children, young people, vulnerable individuals and their families. This module aims to: ● Develop knowledge and understanding of principles of healthcare ethics and English Law. ● Give an understanding of current legal and ethical issues relating to the profession.\\n● Examine the influence of legislation and professional bodies on current healthcare practice for babies, children, young people and vulnerable individuals.",
        "metadata": {
          "type": "module",
          "module_code": "W_HTH5C027R-2025.26",
          "module_title": "Ethical Working Practices in Healthcare",
          "tutor": "Shelley Sanderson",
          "credits": "20",
          "year": "2",
          "semester": "1",
          "course_code": "FD-HPS-25/26",
          "sub_department": "Health"
        }
      },
      {
        "id": "assessment-ethical-working-practices-in-healthcare-presentation",
        "text": "Assessment: Task 1 Presentation (40%)\nModule: Ethical Working Practices in Healthcare\nModule Code: W_HTH5C027R-2025.26\nAcademic Year: 2\nUnit Assessor: Shelley Sanderson\nSubmission Location: Electronic submission.\nDeadline: Friday\nSubmission Format: [Turnitin/Physical/Face-to-Face]\n\nLearning Outcomes:\nLO 2, 4\n\nAssessment Brief:\nAssessment Brief\\nThe following tasks are based on a self-selected identified case study of a healthcare ethical dilemma of\\na child and/or young person. The selected case study must be discussed and agreed with your module\\ntutor prior to submission. Any chosen case must be in the public domain to ensure that codes of\\nconfidentiality in the workplace are met and to protect individuals.\\nTask 1 Presentation (15 minutes) assesses Learning Outcomes (40%)\\nExamining a self-selected case study, give a 15-minute presentation that; Identifies and critically reflects\\nupon ethical dilemmas where they emerge in clinical practice. Your presentation must also include the\\nkey stakeholders in the case and their viewpoints. Evaluate these viewpoints in the identified case study\\nand communicate clearly and effectively their position in relation to ethical approaches.\\nPlease ensure that your presentation is effectively supported with appropriate references and\\nincludes a reference list.",
        "metadata": {
          "type": "assessment",
          "module_code": "W_HTH5C027R-2025.26",
          "module_title": "Ethical Working Practices in Healthcare",
          "assessment_type": "Presentation",
          "weight": "40",
          "word_count": "15 Minutes",
          "deadline": "Friday",
          "year": "2",
          "semester": "1",
          "tutor": "Shelley Sanderson"
        }
      },
      {
        "id": "assessment-ethical-working-practices-in-healthcare-report",
        "text": "Assessment: Task 2 Report (60%)\nModule: Ethical Working Practices in Healthcare\nModule Code: W_HTH5C027R-2025.26\nAcademic Year: 2\nUnit Assessor: Shelley Sanderson\nSubmission Location: Electronic submission.\nDeadline: Friday\nSubmission Format: [Turnitin/Physical/Face-to-Face]\n\nLearning Outcomes:\nLO 1,3\n\nAssessment Brief:\nAssessment Brief\\nThe following tasks are based on a self-selected identified case study of a healthcare ethical dilemma of\\na child and/or young person. The selected case study must be discussed and agreed with your module\\ntutor prior to submission. Any chosen case must be in the public domain to ensure that codes of\\nconfidentiality in the workplace are met and to protect individuals.\\nTask 2 Report (2500 words) assesses Learning Outcomes (60%)\\nWrite a report on your self-selected case study that covers the following aspects in detail.\\n● An application and critical evaluation of relevant key theoretical perspectives that relate to the\\nethical dilemmas in the self-selected case study.\\n● Identify and analyse the impact of legislation on ethical work practices that was applied in the\\nself-selected case study.\\n● Critically evaluate and apply decision making theory that you consider appropriate to the case.\\nPlease ensure that your report is effectively supported with appropriate references and includes\\na reference list.",
        "metadata": {
          "type": "assessment",
          "module_code": "W_HTH5C027R-2025.26",
          "module_title": "Ethical Working Practices in Healthcare",
          "assessment_type": "Report",
          "weight": "60",
          "word_count": "2500",
          "deadline": "Friday",
          "year": "2",
          "semester": "1",
          "tutor": "Shelley Sanderson"
        }
      },
      {
        "id": "module-therapeutic-play-interventions",
        "text": "Module: Therapeutic Play Interventions\nModule Code: W_HTH5C026R-2025.26\nModule Tutor: Paula Jackson\nCredits: 20\nYear: 2\nSemester: 1\n\nLearning Outcomes:\nLearning outcome\\nOn completion of this module students will be able to:\\nKnowledge and Understanding;\\n1. Discuss and evaluate the current context for contemporary childhood and adolescent access to therapeutic play interventions. (K1)\\nCognitive Skills:\\n2. Critically evaluate the current theories of the role of play in child development and the implications for cognitive, social and emotional development. (C1)\\nPractical and Professional Skills:\\n3. Analyse the different therapeutic play strategies employed in the workplace that support children, young people and vulnerable individuals' engagement with play both individually and with peers. (P1)\\nKey Transferable Skills:\\n4. Communicate effectively both written and verbally. (T3)\n\nModule Description:\nModule Descriptor:\\nThis module provides the opportunity to examine the therapeutic play needs of sick children. \\nThe aim of this module is to:\\nDevelop skills and knowledge to support children, young people, vulnerable individuals and their families using therapeutic play methods\\nProvide understanding and knowledge of the use of therapeutic play interventions and techniques in healthcare practice\\nFacilitate high quality practice when using play interventions to support the development of sick children",
        "metadata": {
          "type": "module",
          "module_code": "W_HTH5C026R-2025.26",
          "module_title": "Therapeutic Play Interventions",
          "tutor": "Paula Jackson",
          "credits": "20",
          "year": "2",
          "semester": "1",
          "course_code": "FD-HPS-25/26",
          "sub_department": "Health"
        }
      },
      {
        "id": "assessment-therapeutic-play-interventions-e-portfolio",
        "text": "Assessment: ePortfolio (100%) - 9 Play Plans and 3 Mentor Discussions (3900 word equiv)\nModule: Therapeutic Play Interventions\nModule Code: W_HTH5C026R-2025.26\nAcademic Year: 2\nUnit Assessor: Paula Jackson\nSubmission Location: [Blackboard/Classroom/etc]\nDeadline: 16.01.2026\nSubmission Format: ePortfolio\n\nLearning Outcomes:\nLO 1,2,3,4\n\nAssessment Brief:\nAssessment Brief\\nTask: ePortfolio 100% - 9 Play Plans and 3 Mentor Discussions\\nAssess, plan, implement, evaluate and analyse the different therapeutic play strategies employed in the healthcare setting that support infants, children, young people and vulnerable individuals\\nDevelop play plans which evidence your therapeutic play interventions, skills, knowledge and behaviours. Critically evaluate and link to research and developmental theory, considering the implications for cognitive, social and emotional development.\\nDiscuss and reflect on your learning and experiences.\\n9 x Play Plans – 350 words each\\n3 x Mentor Discussions – 250 words each\\nEquates to 3,900 words in total\\n100% Assessment however use a milestone approach to submit\\nMilestone 1 – TP1 Play Plan, TP2 Play Plan & TP3 Play Plan @350 words each \\nMilestone 2 – TP1 Play Plan x 2, TP2 Play Plan x 2 & TP3 Play Plan x 2 @350 words each\\n  AND\\nTP1, TP2 & TP3 Mentor Discussions @ 250 words each\\n(LO 1,2,3,4) \\n(3900 word equiv)",
        "metadata": {
          "type": "assessment",
          "module_code": "W_HTH5C026R-2025.26",
          "module_title": "Therapeutic Play Interventions",
          "assessment_type": "ePortfolio",
          "weight": "100%",
          "word_count": "3900 word equiv",
          "deadline": "16.01.2026",
          "year": "2",
          "semester": "1",
          "tutor": "Paula Jackson"
        }
      },
      {
        "id": "module-work-based-project",
        "text": "Module: Work Based Project\nModule Code: W_HTH5C028R-2025.26\nModule Tutor: Shelley Sanderson\nCredits: 20\nYear: 2\nSemester: 2\n\nLearning Outcomes:\n21 Learning outcomes On completion of this module students will be able to: Knowledge and Understanding: 1. Evaluate different approaches to research that could provide solutions to problems in the workplace (K2). Cognitive/Intellectual Skills 2. Analyse the ethical considerations involved in undertaking research and demonstrate their application within your own study (C1) Professional Skills 3. Demonstrate innovation and creativity in the development of solutions to work-based problems (P3) Key Transferable Skills 4. Reflect on the research outcomes and recommend an appropriate course of action to enhance working practices (T1).\n\nModule Description:\nModule Descriptor: This module will give the opportunity to select an area of interest relating to the role of the health play specialist to research in more detail, either in practice or theoretically. This will facilitate a deeper knowledge of the chosen area. This module aims to:\\n\\n● Develop knowledge and understanding of the use of investigative techniques in healthcare practice. ● Facilitate a small-scale investigation to make recommendations for improvement in practice and / or provision. ● Promote autonomy when project planning and increase confidence in the decision-making process.",
        "metadata": {
          "type": "module",
          "module_code": "W_HTH5C028R-2025.26",
          "module_title": "Work Based Project",
          "tutor": "Shelley Sanderson",
          "credits": "20",
          "year": "2",
          "semester": "2",
          "course_code": "FD-HPS-25/26",
          "sub_department": "Health"
        }
      },
      {
        "id": "assessment-work-based-project-small-scale-work-based-project",
        "text": "Assessment: Small-scale work-based project (Including UC Ethical Approval) 4000 words (100%)\nModule: Work Based Project\nModule Code: W_HTH5C028R-2025.26\nAcademic Year: 2\nUnit Assessor: Shelley Sanderson\nSubmission Location: [Blackboard/Classroom/etc]\nDeadline: Week 29\nSubmission Format: [Turnitin/Physical/Face-to-Face]\n\nLearning Outcomes:\nLO 1, 2, 3, 4\n\nAssessment Brief:\nAssessment Brief\\nTask 1- Plan and undertake a small-scale work based project. Produce a written evaluation of\\nthe project. (4000 words) (100%) Assess LO’s 1, 2, 3 and 4\\nInvestigate an aspect of healthcare that relates to the role of a health play specialist that you\\nfeel needs consideration. Research the key values and principles pertaining to this to provide\\nfurther insight, solutions and recommendations.\\n● Devise a plan to conduct this small-scale work based project, which will include a clear rationale for\\nyour choice and the research methodology, timescales, consultation, ethical considerations.\\n● Include the potential impact of this small scale research project on the sector.\\n● Conduct a literature review of historical and contemporary literature relating to the selected project\\n● Implement your plan, and carry out your project in your workplace\\n● Analyse, evaluate and interpret appropriate data relating to your project, considering how this data\\nrelates to or impacts on your chosen research focus.\\n● Critically reflect upon your research and make recommendations for the sector.\\nElements of the Work-Based Project will also support and form content for the\\ncompetency evidence for Research and Evidence Based Practice (REB) competencies 1,\\n2 & 3 within the ePortfolio Practice Assessment - Critical Reflection on Practice module.",
        "metadata": {
          "type": "assessment",
          "module_code": "W_HTH5C028R-2025.26",
          "module_title": "Work Based Project",
          "assessment_type": "Small-scale work-based project",
          "weight": "100%",
          "word_count": "4000",
          "deadline": "Week 29",
          "year": "2",
          "semester": "2",
          "tutor": "Shelley Sanderson"
        }
      },
      {
        "id": "module-supporting-emotional-health-and-wellbeing-of-the-sick-child",
        "text": "Module: Supporting Emotional Health and Wellbeing of the Sick Child\nModule Code: W_HTH5C029R-2025.26\nModule Tutor: Paula Jackson\nCredits: 20\nYear: 2\nSemester: 2\n\nLearning Outcomes:\n21 Learning outcomes On completion of this module students will be able to: Knowledge and Understanding: 1. Appraise relevant principles and theories in relation to significant life events and stress, considering the psychological and emotional impact of a healthcare journey on sick babies, children and young people (K1). 2. Examine the impact of safeguarding legislation, policy and procedures in relation to supporting mental health and wellbeing (K3) Cognitive and Intellectual Skills: 3. Evaluate the current strategies and interventions in relation to supporting the mental health and wellbeing of sick babies, children, young people and/or vulnerable individuals (C2). Professional Skills:\\n4. Relate evidence-based practice, and personal and professional value systems to supporting sick children’s emotional health and wellbeing, (P2). Key Transferable Skills: 5. Demonstrate professional autonomy to engage in ethical decision making and support the emotional wellbeing of sick children (T2).\n\nModule Description:\nModule Descriptor: Building on foundational knowledge of child development and the therapeutic use of play, this Level 5 module provides theoretical understanding and practical skills to proactively support the emotional health and wellbeing of sick babies, children, and young people. Learners will explore the impact of a healthcare journey on children's emotional health and wellbeing. The module will explore evidence-informed strategies and interventions to foster resilience, facilitate emotional expression, mitigate distress\\nand trauma, and promote positive coping mechanisms, thus ensuring sustainability within the often challenging healthcare environment. This module aims to: ● Provide knowledge and insight of psychological impact and mental health and wellbeing in babies, children, young people and vulnerable individuals experiencing acute or chronic healthcare journeys. ● Develop evidence-based practice and interventions to address emotional distress, anxiety, grief, and trauma. ● Challenge stereotypes, discriminatory behaviours and promote inclusion.",
        "metadata": {
          "type": "module",
          "module_code": "W_HTH5C029R-2025.26",
          "module_title": "Supporting Emotional Health and Wellbeing of the Sick Child",
          "tutor": "Paula Jackson",
          "credits": "20",
          "year": "2",
          "semester": "2",
          "course_code": "FD-HPS-25/26",
          "sub_department": "Health"
        }
      },
      {
        "id": "assessment-supporting-emotional-health-and-wellbeing-of-the-sick-child-essay",
        "text": "Assessment: Essay (2400 words) 60%\nModule: Supporting Emotional Health and Wellbeing of the Sick Child\nModule Code: W_HTH5C029R-2025.26\nAcademic Year: 2\nUnit Assessor: Paula Jackson\nSubmission Location: [Blackboard/Classroom/etc]\nDeadline: Week 25\nSubmission Format: [Turnitin/Physical/Face-to-Face]\n\nLearning Outcomes:\nL.O. 1 & 2\n\nAssessment Brief:\nTask 1: Essay 2400 words – 60% - L.O. 1 & 2\\nChoose a theory relating to stress and/or significant life events and appraise how they can\\nimpact on individuals' emotional wellbeing.\\nResearch a current topic relating to emotional wellbeing and critically evaluate strategies that\\nsupport individuals affected by it.",
        "metadata": {
          "type": "assessment",
          "module_code": "W_HTH5C029R-2025.26",
          "module_title": "Supporting Emotional Health and Wellbeing of the Sick Child",
          "assessment_type": "Essay",
          "weight": "60%",
          "word_count": "2400",
          "deadline": "Week 25",
          "year": "2",
          "semester": "2",
          "tutor": "Paula Jackson"
        }
      },
      {
        "id": "assessment-supporting-emotional-health-and-wellbeing-of-the-sick-child-reflection",
        "text": "Assessment: Reflection (1600 words) 40%\nModule: Supporting Emotional Health and Wellbeing of the Sick Child\nModule Code: W_HTH5C029R-2025.26\nAcademic Year: 2\nUnit Assessor: Paula Jackson\nSubmission Location: [Blackboard/Classroom/etc]\nDeadline: Week 30\nSubmission Format: [Turnitin/Physical/Face-to-Face]\n\nLearning Outcomes:\nL.O. 3\n\nAssessment Brief:\nTask 2: Personal Development Plan 1600 words – 40% - L.O. 3\\nInclude a reflection of your own personal value systems and approaches in relation to an issue\\nwhich you have identified in your workplace and conclude with a plan to develop and improve\\nyour practices.",
        "metadata": {
          "type": "assessment",
          "module_code": "W_HTH5C029R-2025.26",
          "module_title": "Supporting Emotional Health and Wellbeing of the Sick Child",
          "assessment_type": "Reflection",
          "weight": "40%",
          "word_count": "1600",
          "deadline": "Week 30",
          "year": "2",
          "semester": "2",
          "tutor": "Paula Jackson"
        }
      },
      {
        "id": "module-critical-reflection-on-practice-professional-occupational-standard-epa",
        "text": "Module: Critical Reflection on Practice (Professional occupational standard/EPA)\nModule Code: W_HTH5C030R-2025.26\nModule Tutor: Paula Jackson\nCredits: 40\nYear: 2\nSemester: 1 and 2\n\nLearning Outcomes:\n21 Learning outcomes On completion of this module students will be able to: Knowledge and Understanding: 1. Critically evaluate theoretical perspectives and key principles in relation to evidence-based practice when working as a Healthcare Play Specialist (K1). Cognitive and Intellectual Skills: 2. Analyse legal and ethical working practices and the impact on professional conduct, patient outcomes and culture within the healthcare sector (C1). 3. Analyse and integrate a comprehensive range of theoretical principles and values to address the needs of children, families and fulfil the role of health play specialist (C2). Professional Skills:\\n\\n4. Evaluate a range of practical situations and professional practice in the workplace for personal development (P1). 5. Integrate evidence-based practice throughout all activities within the Health Play Specialist role (P2)(P2). Key Transferable Skills: 7 Critically reflect on practice to support ongoing professional and service development (T1) 6. Demonstrate professional autonomy and independence in the workplace (T2). 7. Facilitate and actively contribute to multidisciplinary team collaboration (T4).\n\nModule Description:\nModule Descriptor: This module is a direct progression and serves as a critical extension of the ‘Developing Professional Practice’ curriculum at level 4. Its primary objective is to facilitate the comprehensive development of the knowledge, skills, and professional behaviours that underpin competent practice as a registered Health Play Specialist. Learning outcomes are mapped to, and fully aligned with, the rigorous professional standards articulated by the Society of Health Play Specialists (SoHPS). This module aims to:\\n\\n● Enable students to critically analyse and integrate theoretical and practical knowledge of health play practice across diverse healthcare environments, ensuring alignment with current evidence-based approaches and the evolving needs of children and families. ● Develop and refine students' professional skills and behaviours to a level of independent competence, empowering them to confidently assess, plan, implement, and evaluate complex health play interventions, strictly adhering to the professional standards. ● Cultivate professional identity and commitment to reflective practice, encouraging students to critically evaluate their own professional development and demonstrate the accountability and autonomy required for registration and ongoing professional growth as a Health Play Specialist.",
        "metadata": {
          "type": "module",
          "module_code": "W_HTH5C030R-2025.26",
          "module_title": "Critical Reflection on Practice (Professional occupational standard/EPA)",
          "tutor": "Paula Jackson",
          "credits": "40",
          "year": "2",
          "semester": "1 and 2",
          "course_code": "FD-HPS-25/26",
          "sub_department": "Health"
        }
      },
      {
        "id": "assessment-critical-reflection-on-practice-professional-occupational-standard-epa-presentation",
        "text": "Assessment: Presentation - 45 mins with 15 min Q&A (40%)\nModule: Critical Reflection on Practice (Professional occupational standard/EPA)\nModule Code: W_HTH5C030R-2025.26\nAcademic Year: 2\nUnit Assessor: Paula Jackson\nSubmission Location: [Blackboard/Classroom/etc]\nDeadline: [Missing Data]\nSubmission Format: [Turnitin/Physical/Face-to-Face]\n\nLearning Outcomes:\nLO 3, 5, 7\n\nAssessment Brief:\n[Missing Data]",
        "metadata": {
          "type": "assessment",
          "module_code": "W_HTH5C030R-2025.26",
          "module_title": "Critical Reflection on Practice (Professional occupational standard/EPA)",
          "assessment_type": "Presentation",
          "weight": "40",
          "word_count": "45 minutess with 15 minutes Q&A",
          "deadline": "[Missing Data]",
          "year": "2",
          "semester": "1 and 2",
          "tutor": "Paula Jackson"
        }
      },
      {
        "id": "assessment-critical-reflection-on-practice-professional-occupational-standard-epa-professional-discussion",
        "text": "Assessment: Professional Discussion - 90 mins (60%)\nModule: Critical Reflection on Practice (Professional occupational standard/EPA)\nModule Code: W_HTH5C030R-2025.26\nAcademic Year: 2\nUnit Assessor: Paula Jackson\nSubmission Location: [Blackboard/Classroom/etc]\nDeadline: [Missing Data]\nSubmission Format: [Turnitin/Physical/Face-to-Face]\n\nLearning Outcomes:\nLO 1, 2, 4, 6, 8\n\nAssessment Brief:\n[Missing Data]",
        "metadata": {
          "type": "assessment",
          "module_code": "W_HTH5C030R-2025.26",
          "module_title": "Critical Reflection on Practice (Professional occupational standard/EPA)",
          "assessment_type": "Professional Discussion",
          "weight": "60",
          "word_count": "90 minutes",
          "deadline": "[Missing Data]",
          "year": "2",
          "semester": "1 and 2",
          "tutor": "Paula Jackson"
        }
      }
]